docs/README_template.md
docs/__init__.py
docs/classes/README.md
docs/classes/README_references.md
docs/classes/app_and_config.md
docs/classes/app_and_config_references.md
docs/classes/audiovisual.md
docs/classes/audiovisual_references.md
docs/classes/controls.md
docs/classes/controls_references.md
docs/classes/data_elements.md
docs/classes/data_elements_references.md
docs/classes/layout.md
docs/classes/layout_references.md
docs/classes/text_elements.md
docs/classes/text_elements_references.md
docs/classes/utilities.md
docs/classes/utilities_references.md
docs/events/README.md
docs/events/button_events.md
docs/events/element_events.md
docs/events/keyboard_events.md
docs/events/lifecycle_events.md
docs/events/upload_events.md
docs/events/value_events.md
docs/mechanics/AGENTS.md
docs/mechanics/README.md
docs/mechanics/application_structure.md
docs/mechanics/authentication.md
docs/mechanics/background_execution.md
docs/mechanics/binding_and_state.md
docs/mechanics/coding_style.md
docs/mechanics/configuration_deployment.md
docs/mechanics/container_updates.md
docs/mechanics/custom_components.md
docs/mechanics/data_modeling.md
docs/mechanics/event_binding.md
docs/mechanics/javascript_integration.md
docs/mechanics/pages.md
docs/mechanics/poetry_setup.md
docs/mechanics/routing.md
docs/mechanics/styling.md
docs/mechanics/sub_pages.md
docs/mechanics/testing.md
docs/mechanics/threejs_integration.md
docs/nicegui_prompt.md
docs/project_creation_guide.md
docs/prompt_config.yaml
docs/testing.md
nice_vibes/__init__.py
nice_vibes/cli.py
nice_vibes/mcp/README.md
nice_vibes/mcp/__init__.py
nice_vibes/mcp/__main__.py
nice_vibes/mcp/media/windsurf_mcp_server.png
nice_vibes/mcp/server.py
nice_vibes/mcp/test_client.py
samples/README.md
samples/README_template.md
samples/calculator/main.py
samples/cone_spray/README.md
samples/cone_spray/animated.gif
samples/cone_spray/cone_spray.js
samples/cone_spray/cone_spray_scene.py
samples/cone_spray/main.py
samples/cone_spray/screenshot.jpg
nice_vibes-0.1.4.dist-info/LICENSE
nice_vibes-0.1.4.dist-info/METADATA
nice_vibes-0.1.4.dist-info/WHEEL
nice_vibes-0.1.4.dist-info/entry_points.txt
nice_vibes-0.1.4.dist-info/RECORD
