Metadata-Version: 2.3
Name: nice-vibes
Version: 0.1.4
Summary: Developing beautiful NiceGUI applications with AI
License: MIT
Keywords: nicegui,ai,prompts,ui,web,framework,coding-assistant,llm
Author: Michael Ikemann
Author-email: michael.ikemann@gmail.com
Requires-Python: >=3.12,<4.0
Classifier: Development Status :: 4 - Beta
Classifier: Intended Audience :: Developers
Classifier: License :: OSI Approved :: MIT License
Classifier: Operating System :: OS Independent
Classifier: Programming Language :: Python :: 3
Classifier: Programming Language :: Python :: 3.12
Classifier: Programming Language :: Python :: 3.13
Classifier: Topic :: Software Development :: Libraries :: Python Modules
Classifier: Topic :: Software Development :: User Interfaces
Classifier: Topic :: Scientific/Engineering :: Artificial Intelligence
Classifier: Typing :: Typed
Requires-Dist: mcp (>=1.0.0)
Requires-Dist: nicegui (>=3.3.1,<4.0.0)
Requires-Dist: opencv-python (>=4.12.0.88,<5.0.0.0)
Requires-Dist: pillow (>=12.0.0,<13.0.0)
Requires-Dist: pyyaml (>=6.0)
Requires-Dist: yfinance (>=0.2.66,<0.3.0)
Project-URL: Documentation, https://github.com/Alyxion/nice-vibes#readme
Project-URL: Homepage, https://github.com/Alyxion/nice-vibes
Project-URL: Issues, https://github.com/Alyxion/nice-vibes/issues
Project-URL: Repository, https://github.com/Alyxion/nice-vibes.git
